tap_readme/__init__.py
tap_readme/__main__.py
tap_readme/client.py
tap_readme/streams.py
tap_readme/tap.py
tap_readme-0.3.5.dist-info/METADATA
tap_readme-0.3.5.dist-info/WHEEL
tap_readme-0.3.5.dist-info/entry_points.txt
tap_readme-0.3.5.dist-info/licenses/LICENSE
tap_readme-0.3.5.dist-info/RECORD
